sde_sim_rs/__init__.py
sde_sim_rs/__init__.pyi
sde_sim_rs/py.typed
sde_sim_rs/sde_sim_rs.pypy311-pp73-arm-linux-gnu.so
sde_sim_rs-0.4.0.dist-info/METADATA
sde_sim_rs-0.4.0.dist-info/WHEEL
sde_sim_rs-0.4.0.dist-info/licenses/LICENSE.txt
sde_sim_rs-0.4.0.dist-info/RECORD
