Metadata-Version: 2.4
Name: sde-sim-rs
Version: 0.4.0
Classifier: Development Status :: 3 - Alpha
Classifier: Intended Audience :: Science/Research
Classifier: Intended Audience :: Developers
Classifier: Intended Audience :: Financial and Insurance Industry
Classifier: License :: OSI Approved :: MIT License
Classifier: Programming Language :: Rust
Classifier: Programming Language :: Python
Classifier: Programming Language :: Python :: 3
Classifier: Programming Language :: Python :: 3.11
Classifier: Programming Language :: Python :: 3.12
Classifier: Programming Language :: Python :: 3.13
Classifier: Programming Language :: Python :: 3 :: Only
Classifier: Programming Language :: Python :: Implementation :: CPython
Classifier: Topic :: Software Development
Classifier: Topic :: Scientific/Engineering
Classifier: Typing :: Typed
Classifier: Operating System :: Microsoft :: Windows
Classifier: Operating System :: Unix
Classifier: Operating System :: MacOS
Requires-Dist: numpy>=1.24.4
Requires-Dist: patchelf>=0.17.2.2
Requires-Dist: polars>=1.8.2
License-File: LICENSE.txt
Summary: Powerful and flexible stochastic differential equation (quasi) Monte-Carlo simulation library written in Rust with Python bindings
Author-email: Alexander Schierbeck-Hansen <aschii85@protonmail.com>
License-Expression: MIT
Requires-Python: >=3.11, <3.14
Project-URL: Homepage, https://github.com/Aschii85/sde-sim-rs
Project-URL: Repository, https://github.com/Aschii85/sde-sim-rs.git
